IQM_Vis/__init__.py
IQM_Vis/ui_wrapper.py
IQM_Vis/version.py
IQM_Vis/UI/__init__.py
IQM_Vis/UI/custom_widgets.py
IQM_Vis/UI/experiment_mode_2AFC.py
IQM_Vis/UI/experiment_mode_JND.py
IQM_Vis/UI/images.py
IQM_Vis/UI/layout.py
IQM_Vis/UI/main.py
IQM_Vis/UI/style-dark.css
IQM_Vis/UI/style-light.css
IQM_Vis/UI/threads.py
IQM_Vis/UI/utils.py
IQM_Vis/UI/widgets.py
IQM_Vis/data_handlers/__init__.py
IQM_Vis/data_handlers/data_api.py
IQM_Vis/data_handlers/data_api_abstract.py
IQM_Vis/examples/__init__.py
IQM_Vis/examples/all.py
IQM_Vis/examples/dataset.py
IQM_Vis/examples/dists.py
IQM_Vis/examples/kodak.py
IQM_Vis/examples/KODAK_dataset/__init__.py
IQM_Vis/examples/images/HIQM.csv
IQM_Vis/examples/images/__init__.py
IQM_Vis/examples/images/waves1.jpeg
IQM_Vis/examples/images/waves2.jpeg
IQM_Vis/examples/images/waves3.jpeg
IQM_Vis/metrics/__init__.py
IQM_Vis/metrics/metric_utils.py
IQM_Vis/metrics/non_perceptual.py
IQM_Vis/metrics/perceptual_DL.py
IQM_Vis/metrics/perceptual_trad.py
IQM_Vis/metrics/NLPD_torch/__init__.py
IQM_Vis/metrics/NLPD_torch/pyramids.py
IQM_Vis/metrics/NLPD_torch/utils/__init__.py
IQM_Vis/metrics/NLPD_torch/utils/conv.py
IQM_Vis/metrics/SSIM/__init__.py
IQM_Vis/metrics/SSIM/ssim.py
IQM_Vis/transforms/__init__.py
IQM_Vis/transforms/additive_noise.py
IQM_Vis/transforms/affine.py
IQM_Vis/transforms/effects.py
IQM_Vis/utils/__init__.py
IQM_Vis/utils/gui_utils.py
IQM_Vis/utils/image_utils.py
IQM_Vis/utils/plot_utils.py
IQM_Vis/utils/save_utils.py
iqm_vis-1.0.1.dist-info/licenses/LICENSE
tests/QtBot_utils.py
tests/__init__.py
tests/conftest.py
tests/test_metrics.py
tests/test_transforms.py
iqm_vis-1.0.1.dist-info/METADATA
iqm_vis-1.0.1.dist-info/WHEEL
iqm_vis-1.0.1.dist-info/top_level.txt
iqm_vis-1.0.1.dist-info/RECORD
