Metadata-Version: 2.4
Name: IQM-Vis
Version: 1.0.1
Summary: Extendable user interface for the assessment of transformations on image metrics.
Author: Matt Clifford
Author-email: matt.clifford@bristol.ac.uk
License-File: LICENSE
Requires-Dist: numpy>=1.23.4
Requires-Dist: PyQt6==6.5.3
Requires-Dist: PyQt6-Qt6==6.5.3
Requires-Dist: PyQt6-sip==13.6
Requires-Dist: opencv-python-headless>=4.6.0.66
Requires-Dist: Pillow>=9.2.0
Requires-Dist: scikit-image>=0.19.3
Requires-Dist: matplotlib>=3.6.1
Requires-Dist: torch>=1.13.1
Requires-Dist: torchmetrics>=1.2.0
Requires-Dist: lpips>=0.1.4
Requires-Dist: DISTS-pytorch>=0.1
Requires-Dist: torchvision>=0.14.1
Requires-Dist: pandas>=2.0.0
Requires-Dist: scipy>=1.9.3
Requires-Dist: notebook
Requires-Dist: filetype
Dynamic: author
Dynamic: author-email
Dynamic: description
Dynamic: description-content-type
Dynamic: license-file
Dynamic: requires-dist
Dynamic: summary
